MANIFEST.in
README.rst
setup.py
./blackmamba/__init__.py
./blackmamba/config.py
./blackmamba/log.py
./blackmamba/system.py
./blackmamba/update.py
./blackmamba/ide/__init__.py
./blackmamba/ide/action.py
./blackmamba/ide/annotation.py
./blackmamba/ide/script.py
./blackmamba/ide/source.py
./blackmamba/ide/tab.py
./blackmamba/script/__init__.py
./blackmamba/script/action_quickly.py
./blackmamba/script/analyze.py
./blackmamba/script/clear_annotations.py
./blackmamba/script/close_all_tabs_except_current_one.py
./blackmamba/script/drag_and_drop.py
./blackmamba/script/find_usages.py
./blackmamba/script/jump_to_definition.py
./blackmamba/script/jump_to_line.py
./blackmamba/script/new_file.py
./blackmamba/script/new_tab.py
./blackmamba/script/open_quickly.py
./blackmamba/script/outline_quickly.py
./blackmamba/script/run_quickly.py
./blackmamba/script/run_unit_tests.py
./blackmamba/script/search_dash.py
./blackmamba/script/show_documentation.py
./blackmamba/script/toggle_comments.py
./blackmamba/uikit/__init__.py
./blackmamba/uikit/autolayout.py
./blackmamba/uikit/keyboard.py
./blackmamba/uikit/picker.py
./blackmamba/uikit/table.py
./blackmamba/util/__init__.py
./blackmamba/util/path.py
./blackmamba/util/runtime.py
blackmamba.egg-info/PKG-INFO
blackmamba.egg-info/SOURCES.txt
blackmamba.egg-info/dependency_links.txt
blackmamba.egg-info/top_level.txt