Metadata-Version: 1.1
Name: blackmamba
Version: 1.0.2
Summary: Pythonista on steroids
Home-page: https://github.com/zrzka/blackmamba
Author: Robert Vojta
Author-email: UNKNOWN
License: MIT
Keywords: pythonista ios
Platform: UNKNOWN
Classifier: Development Status :: 5 - Production/Stable
Classifier: License :: OSI Approved :: MIT License
Classifier: Operating System :: iOS
Classifier: Programming Language :: Python :: 3.5
Classifier: Topic :: Software Development
